LICENSE
MANIFEST.in
README.rst
pytest_sqitch.py
setup.py
pytest_sqitch/__init__.py
pytest_sqitch/client.py
pytest_sqitch.egg-info/PKG-INFO
pytest_sqitch.egg-info/SOURCES.txt
pytest_sqitch.egg-info/dependency_links.txt
pytest_sqitch.egg-info/entry_points.txt
pytest_sqitch.egg-info/requires.txt
pytest_sqitch.egg-info/top_level.txt